{
  "@subject": "isonderdeelid",
  "@type": "http://rws.org/disk",
  "@context": {
    "@base": "http://rws.org/disk/id/",
    "rws": "http://rws.org/disk/def/",
    "rdf": "http://www.w3.org/1999/02/22-rdf-syntax-ns#",
    "rdfs": "http://www.w3.org/2000/01/rdf-schema#",
    "id": "dct:identifier",
    "complexid": "rws:complexIdentificatie",
    "beheercode": "rws:beheercode",
    "naam": "rdfs:label",
    "omschrijving": "dct:description",
    "beheerobjectsoort": "rws:beheerObjectSoort",
    "aard": "rdf:type",
    "netwerk": "rws:netwerk",
    "classificatie": "rws:classificatie",
    "bpscoderingid": "rws:bpsCoderingIdentificatie",
    "route": "rws:route",
    "traj_id": "rws:trajectIdentificatie",
    "relatie_tot_weg": "rws:relatieTotWeg",
    "provincie2": "rws:provincie2",
    "gemeente1": "rws:gemeente1",
    "gemeente2": "rws:gemeente2",
    "isinactive": "rws:isInactive",
    "waterweg": "rws:waterweg",
    "id_miok": "rws:id_miok",
    "instantieid": "rws:instantieId",
    "userid_insert": "dct:creator",
    "date_insert": "dct:created",
    "userid_modified": "rws:useridModified",
    "date_modified": "dct:modified",
    "timestamp": "rws:timestamp",
    "ihonderdeelid": "rws:ihonderdeelid",
    "locatie": "rws:locatie",
    "elementsoort": "rws:elementsoort",
    "hoeveelheid": "rws:hoeveelheid",
    "eenheid": "rws:eenheid",
    "materiaal": "rws:materiaal",
    "beheerobjectid": "rws:beheerobjectid",
    "isonderdeelid": "rws:isonderdeelid",
    "bouwdeelsoort": "rws:bouwdeelsoort",
    "vaarweg": "rws:vaarweg",
    "waterweghmtot": "rws:waterweghmtot",
    "rdx": "rws:rdx",
    "rdy": "rws:rdy",
    "stichtingsjaar": "rws:stichtingsjaar",
    "status": "rws:status",
    "sloopjaar": "rws:sloopjaar",
    "eigenaar": "rws:eigenaar",
    "beheerder": "rws:beheerder",
    "ondplicht": "rws:ondplicht",
    "beheergebied": "rws:beheergebied",
    "inspinst": "rws:inspinst",
    "provincie1": "rws:provincie1"
  }
}
